LICENSE
MANIFEST.in
README.rst
setup.cfg
setup.py
src/sentry_quotas/__init__.py
src/sentry_quotas/models.py
src/sentry_quotas/plugin.py
src/sentry_quotas.egg-info/PKG-INFO
src/sentry_quotas.egg-info/SOURCES.txt
src/sentry_quotas.egg-info/dependency_links.txt
src/sentry_quotas.egg-info/entry_points.txt
src/sentry_quotas.egg-info/not-zip-safe
src/sentry_quotas.egg-info/requires.txt
src/sentry_quotas.egg-info/top_level.txt