Metadata-Version: 1.0
Name: sentry-quotas
Version: 0.1.6
Summary: A Sentry extension which add hard limits to projects.
Home-page: http://github.com/getsentry/sentry-quotas
Author: David Cramer
Author-email: dcramer@gmail.com
License: Apache License 2.0
Platform: UNKNOWN
Classifier: Framework :: Django
Classifier: Intended Audience :: Developers
Classifier: Intended Audience :: System Administrators
Classifier: Operating System :: OS Independent
Classifier: Topic :: Software Development
